 <record model="ir.ui.view" id="session_gantt_view">
            <field name="name">session.gantt</field>
            <field name="model">openacademy.session</field>
            <field name="arch" type="xml">
                <gantt string="Session Gantt"
                       date_start="start_date" date_delay="hours"
                       default_group_by='instructor_id'>
                    <!-- <field name="name"/> this is not required after Odoo 10.0 -->
                </gantt>
            </field>
        </record>